piconetcontrol/__init__.py
piconetcontrol/__main__.py
piconetcontrol/client/__init__.py
piconetcontrol/client/client.py
piconetcontrol/client/gen_ssl.sh
piconetcontrol/client/setup.py
piconetcontrol/client/update.py
piconetcontrol/server/__init__.py
piconetcontrol/server/main.py
piconetcontrol/server/server_base.py
piconetcontrol/server/server_pico.py
piconetcontrol/server/server_rpi.py
piconetcontrol/server/utils/test_wifi.py
piconetcontrol/server/utils/wipe_root.py
piconetcontrol/utils.py
piconetcontrol-0.3.0.dist-info/LICENSE
piconetcontrol-0.3.0.dist-info/METADATA
piconetcontrol-0.3.0.dist-info/WHEEL
piconetcontrol-0.3.0.dist-info/entry_points.txt
piconetcontrol-0.3.0.dist-info/RECORD
