Metadata-Version: 2.1
Name: piconetcontrol
Version: 0.3.0
Summary: Client-server package to remotely control a Raspberrypi Pi Pico W.
License: MIT
Author: Matthias Zeller
Author-email: matthias.gilles.zeller@gmail.com
Requires-Python: >=3.11,<4.0
Classifier: Intended Audience :: Developers
Classifier: License :: OSI Approved :: MIT License
Classifier: Operating System :: OS Independent
Classifier: Programming Language :: Python :: 3
Classifier: Programming Language :: Python :: 3.11
Classifier: Programming Language :: Python :: 3.12
Classifier: Programming Language :: Python :: 3.9
Classifier: Topic :: Software Development :: Libraries :: Python Modules
Classifier: Topic :: System :: Hardware
Classifier: Topic :: System :: Networking
Requires-Dist: beautifulsoup4 (>=4.12.3,<5.0.0)
Requires-Dist: colorama (>=0.4.6,<0.5.0)
Requires-Dist: mpremote (>=1.24.1,<2.0.0)
Requires-Dist: polling2 (>=0.5.0,<0.6.0)
Requires-Dist: pyudev (>=0.24.3,<0.25.0)
Requires-Dist: simple-term-menu (>=1.6.6,<2.0.0)
